doccron/__init__.py
doccron/cron_job.py
doccron/exceptions.py
doccron/interval_job.py
doccron/table.py
doccron/timezone.py
doccron-1.6.2.dist-info/LICENSE
doccron-1.6.2.dist-info/WHEEL
doccron-1.6.2.dist-info/METADATA
doccron-1.6.2.dist-info/RECORD
