Metadata-Version: 2.1
Name: doccron
Version: 1.6.2
Summary: Schedule with Docstrings
Home-page: https://github.com/roniemartinez/DocCron
License: MIT
Keywords: crontab,cron,docstring
Author: Ronie Martinez
Author-email: ronmarti18@gmail.com
Requires-Python: >=3.7,<4.0
Classifier: Development Status :: 5 - Production/Stable
Classifier: License :: OSI Approved :: MIT License
Classifier: Programming Language :: Python :: 3
Classifier: Programming Language :: Python :: 3.10
Classifier: Programming Language :: Python :: 3.7
Classifier: Programming Language :: Python :: 3.8
Classifier: Programming Language :: Python :: 3.9
Classifier: Programming Language :: Python :: Implementation :: CPython
Requires-Dist: python-dateutil (>=2.8.1,<3.0.0)
Project-URL: Donate, https://github.com/sponsors/roniemartinez
Project-URL: Repository, https://github.com/roniemartinez/DocCron
